{"title":"Sterenn","url":"https://www.mjctregunc.fr/%C3%A9v%C3%A9nements/programmation/","favicon":"https://www.mjctregunc.fr/%C3%A9v%C3%A9nements/programmation/favicon.ico","elements":[{"title":"Concert Punk/Metal","contents":"<div class=\"cc-m-hgrid-column\" style=\"width: 49%;\">\n        <div id=\"cc-matrix-6121116425\"><div id=\"cc-m-20059878125\" class=\"j-module n j-imageSubtitle \"><figure class=\"cc-imagewrapper cc-m-image-align-1 cc-m-width-maxed\">\n<a href=\"https://www.mjctregunc.fr/événements/programmation-sterenn/week-end-culturel-malgache/\" target=\"_blank\"><img srcset=\"https://image.jimcdn.com/app/cms/image/transf/dimension=320x10000:format=jpg/path/s79e3f2024b935e45/image/i92d358d948cce17c/version/1764250403/image.jpg 320w, https://image.jimcdn.com/app/cms/image/transf/dimension=456x10000:format=jpg/path/s79e3f2024b935e45/image/i92d358d948cce17c/version/1764250403/image.jpg 456w, https://image.jimcdn.com/app/cms/image/transf/dimension=640x10000:format=jpg/path/s79e3f2024b935e45/image/i92d358d948cce17c/version/1764250403/image.jpg 640w, https://image.jimcdn.com/app/cms/image/transf/none/path/s79e3f2024b935e45/image/i92d358d948cce17c/version/1764250403/image.jpg 842w\" sizes=\"(min-width: 456px) 456px, 100vw\" id=\"cc-m-imagesubtitle-image-20059878125\" src=\"https://image.jimcdn.com/app/cms/image/transf/dimension=456x10000:format=jpg/path/s79e3f2024b935e45/image/i92d358d948cce17c/version/1764250403/image.jpg\" alt=\"\" class=\"\" data-src-width=\"842\" data-src-height=\"1191\" data-src=\"https://image.jimcdn.com/app/cms/image/transf/dimension=456x10000:format=jpg/path/s79e3f2024b935e45/image/i92d358d948cce17c/version/1764250403/image.jpg\" data-image-id=\"11953355225\"></a>    \n\n</figure>\n\n<div class=\"cc-clear\"></div>\n</div></div>    </div>\n            <div class=\"cc-m-hgrid-separator\" data-display=\"cms-only\"><div></div></div>\n        <div class=\"cc-m-hgrid-column last\" style=\"width: 49%;\">\n        <div id=\"cc-matrix-6121116525\"><div id=\"cc-m-20059878225\" class=\"j-module n j-header \"><h1 class=\"\" id=\"cc-m-header-20059878225\">Concert Punk/Metal</h1></div><div id=\"cc-m-20059878325\" class=\"j-module n j-header \"><h2 class=\"\" id=\"cc-m-header-20059878325\">Samedi 17 janvier 2026</h2></div><div id=\"cc-m-20059878425\" class=\"j-module n j-header \"><h2 class=\"\" id=\"cc-m-header-20059878425\">concert</h2></div><div id=\"cc-m-20059878525\" class=\"j-module n j-text \"><p style=\"text-align: center;\">\n    <strong><em><span style=\"color: #454545;\">Après le succès de l'an dernier, la soirée hivernale consacrée au rock revient au Sterenn ! En collaboration avec la Vonologie, une soirée punk / metal\n    avec 4 groupes issus de&nbsp;la scène bretonne et nationale, avec une attention particulière à la présence féminine.</span></em></strong>\n</p>\n\n<p>\n    &nbsp;\n</p>\n\n<p>\n    &nbsp;\n</p>\n\n<p>\n    &nbsp;\n</p></div><div id=\"cc-m-20059878625\" class=\"j-module n j-callToAction \"><div class=\"j-calltoaction-wrapper j-calltoaction-align-2\">\n    <a class=\"j-calltoaction-link j-calltoaction-link-style-3\" data-action=\"button\" href=\"https://www.mjctregunc.fr/événements/programmation/concert-de-saison/\" target=\"_blank\" data-title=\"Voir le programme\">\n        Voir le programme    </a>\n</div>\n</div></div>    </div>\n    \n<div class=\"cc-m-hgrid-overlay\" data-display=\"cms-only\"></div>\n\n<br class=\"cc-clear\">","link":"https://www.mjctregunc.fr/%C3%A9v%C3%A9nements/programmation-sterenn/week-end-culturel-malgache/","retrieved":1764530898251},{"title":"Théâtre musical","contents":"<div class=\"cc-m-hgrid-column\" style=\"width: 49%;\">\n        <div id=\"cc-matrix-6115544225\"><div id=\"cc-m-20030399525\" class=\"j-module n j-imageSubtitle \"><figure class=\"cc-imagewrapper cc-m-image-align-1 cc-m-width-maxed\">\n<a href=\"https://www.mjctregunc.fr/événements/programmation-sterenn/week-end-culturel-malgache/\" target=\"_blank\"><img srcset=\"https://image.jimcdn.com/app/cms/image/transf/dimension=320x10000:format=jpg/path/s79e3f2024b935e45/image/i25e827ebcb9487c5/version/1756823091/image.jpg 320w, https://image.jimcdn.com/app/cms/image/transf/dimension=456x10000:format=jpg/path/s79e3f2024b935e45/image/i25e827ebcb9487c5/version/1756823091/image.jpg 456w, https://image.jimcdn.com/app/cms/image/transf/dimension=640x10000:format=jpg/path/s79e3f2024b935e45/image/i25e827ebcb9487c5/version/1756823091/image.jpg 640w, https://image.jimcdn.com/app/cms/image/transf/dimension=912x10000:format=jpg/path/s79e3f2024b935e45/image/i25e827ebcb9487c5/version/1756823091/image.jpg 912w\" sizes=\"(min-width: 456px) 456px, 100vw\" id=\"cc-m-imagesubtitle-image-20030399525\" src=\"https://image.jimcdn.com/app/cms/image/transf/dimension=456x10000:format=jpg/path/s79e3f2024b935e45/image/i25e827ebcb9487c5/version/1756823091/image.jpg\" alt=\"\" class=\"\" data-src-width=\"4032\" data-src-height=\"3024\" data-src=\"https://image.jimcdn.com/app/cms/image/transf/dimension=456x10000:format=jpg/path/s79e3f2024b935e45/image/i25e827ebcb9487c5/version/1756823091/image.jpg\" data-image-id=\"11928035325\"></a>    \n\n</figure>\n\n<div class=\"cc-clear\"></div>\n</div></div>    </div>\n            <div class=\"cc-m-hgrid-separator\" data-display=\"cms-only\"><div></div></div>\n        <div class=\"cc-m-hgrid-column last\" style=\"width: 49%;\">\n        <div id=\"cc-matrix-6115544325\"><div id=\"cc-m-20030399625\" class=\"j-module n j-header \"><h1 class=\"\" id=\"cc-m-header-20030399625\">Théâtre musical</h1></div><div id=\"cc-m-20030399725\" class=\"j-module n j-header \"><h2 class=\"\" id=\"cc-m-header-20030399725\">Dimanche 30 novembre</h2></div><div id=\"cc-m-20030399825\" class=\"j-module n j-header \"><h2 class=\"\" id=\"cc-m-header-20030399825\">Saison jeune Public</h2></div><div id=\"cc-m-20030399925\" class=\"j-module n j-text \"><p style=\"text-align: center;\">\n    <span style=\"color: #454545;\"><strong>LES GLANDS de la compagnie Tranx</strong></span>\n</p>\n\n<p>\n    &nbsp;\n</p>\n\n<p>\n    &nbsp;\n</p>\n\n<p>\n    &nbsp;\n</p></div><div id=\"cc-m-20030400025\" class=\"j-module n j-callToAction \"><div class=\"j-calltoaction-wrapper j-calltoaction-align-2\">\n    <a class=\"j-calltoaction-link j-calltoaction-link-style-3\" data-action=\"button\" href=\"https://www.mjctregunc.fr/événements/programmation/saison-jeune-public/\" target=\"_blank\" data-title=\"Voir le programme\">\n        Voir le programme    </a>\n</div>\n</div></div>    </div>\n    \n<div class=\"cc-m-hgrid-overlay\" data-display=\"cms-only\"></div>\n\n<br class=\"cc-clear\">","link":"https://www.mjctregunc.fr/%C3%A9v%C3%A9nements/programmation-sterenn/week-end-culturel-malgache/","retrieved":1764530898251},{"title":"Stage de Danse","contents":"<div class=\"cc-m-hgrid-column\" style=\"width: 49%;\">\n        <div id=\"cc-matrix-6119322425\"><div id=\"cc-m-20050379725\" class=\"j-module n j-imageSubtitle \"><figure class=\"cc-imagewrapper cc-m-image-align-1 cc-m-width-maxed\">\n<a href=\"https://www.mjctregunc.fr/événements/programmation-sterenn/week-end-culturel-malgache/\" target=\"_blank\"><img srcset=\"https://image.jimcdn.com/app/cms/image/transf/dimension=320x10000:format=jpg/path/s79e3f2024b935e45/image/ief4cfccb4b7d7823/version/1761828642/image.jpg 320w, https://image.jimcdn.com/app/cms/image/transf/dimension=456x10000:format=jpg/path/s79e3f2024b935e45/image/ief4cfccb4b7d7823/version/1761828642/image.jpg 456w, https://image.jimcdn.com/app/cms/image/transf/dimension=640x10000:format=jpg/path/s79e3f2024b935e45/image/ief4cfccb4b7d7823/version/1761828642/image.jpg 640w, https://image.jimcdn.com/app/cms/image/transf/dimension=912x10000:format=jpg/path/s79e3f2024b935e45/image/ief4cfccb4b7d7823/version/1761828642/image.jpg 912w\" sizes=\"(min-width: 456px) 456px, 100vw\" id=\"cc-m-imagesubtitle-image-20050379725\" src=\"https://image.jimcdn.com/app/cms/image/transf/dimension=456x10000:format=jpg/path/s79e3f2024b935e45/image/ief4cfccb4b7d7823/version/1761828642/image.jpg\" alt=\"\" class=\"\" data-src-width=\"6016\" data-src-height=\"4016\" data-src=\"https://image.jimcdn.com/app/cms/image/transf/dimension=456x10000:format=jpg/path/s79e3f2024b935e45/image/ief4cfccb4b7d7823/version/1761828642/image.jpg\" data-image-id=\"11944850925\"></a>    \n\n</figure>\n\n<div class=\"cc-clear\"></div>\n</div></div>    </div>\n            <div class=\"cc-m-hgrid-separator\" data-display=\"cms-only\"><div></div></div>\n        <div class=\"cc-m-hgrid-column last\" style=\"width: 49%;\">\n        <div id=\"cc-matrix-6119322525\"><div id=\"cc-m-20050379825\" class=\"j-module n j-header \"><h1 class=\"\" id=\"cc-m-header-20050379825\">Stage de Danse</h1></div><div id=\"cc-m-20050379925\" class=\"j-module n j-header \"><h2 class=\"\" id=\"cc-m-header-20050379925\">15 &amp;16 Nov 2025 Stage de Danse contemporaine</h2></div><div id=\"cc-m-20050380125\" class=\"j-module n j-text \"><p style=\"text-align: center;\">\n    - avec Laure FOUARD&nbsp; de la <strong><a href=\"https://delencresurlespieds.com/?page_id=886\" target=\"_blank\" title=\"https://delencresurlespieds.com/?page_id=886\">Cie De l'encre sur les Pieds et\n    <span style=\"color: #674baa;\">La</span></a></strong><br>\n    <span style=\"color: #674baa;\"><strong>T.R.O.U.P.E</strong></span>\n</p>\n\n<p>\n    &nbsp;\n</p>\n\n<p>\n    &nbsp;\n</p>\n\n<p>\n    &nbsp;\n</p></div><div id=\"cc-m-20050380225\" class=\"j-module n j-callToAction \"><div class=\"j-calltoaction-wrapper j-calltoaction-align-2\">\n    <a class=\"j-calltoaction-link j-calltoaction-link-style-3\" data-action=\"button\" href=\"https://www.mjctregunc.fr/événements/stages-de-danse/\" target=\"_blank\" data-title=\"Voir le programme\">\n        Voir le programme    </a>\n</div>\n</div></div>    </div>\n    \n<div class=\"cc-m-hgrid-overlay\" data-display=\"cms-only\"></div>\n\n<br class=\"cc-clear\">","link":"https://www.mjctregunc.fr/%C3%A9v%C3%A9nements/programmation-sterenn/week-end-culturel-malgache/","retrieved":1764530898251},{"title":"Week-end culture malgache","contents":"<div class=\"cc-m-hgrid-column\" style=\"width: 49%;\">\n        <div id=\"cc-matrix-6111530125\"><div id=\"cc-m-20008204125\" class=\"j-module n j-imageSubtitle \"><figure class=\"cc-imagewrapper cc-m-image-align-1 cc-m-width-maxed\">\n<a href=\"https://www.mjctregunc.fr/événements/programmation-sterenn/week-end-culturel-malgache/\" target=\"_blank\"><img srcset=\"https://image.jimcdn.com/app/cms/image/transf/dimension=320x10000:format=png/path/s79e3f2024b935e45/image/if47a880e4e5bb635/version/1750857970/image.png 320w, https://image.jimcdn.com/app/cms/image/transf/dimension=456x10000:format=png/path/s79e3f2024b935e45/image/if47a880e4e5bb635/version/1750857970/image.png 456w, https://image.jimcdn.com/app/cms/image/transf/dimension=640x10000:format=png/path/s79e3f2024b935e45/image/if47a880e4e5bb635/version/1750857970/image.png 640w, https://image.jimcdn.com/app/cms/image/transf/dimension=912x10000:format=png/path/s79e3f2024b935e45/image/if47a880e4e5bb635/version/1750857970/image.png 912w\" sizes=\"(min-width: 456px) 456px, 100vw\" id=\"cc-m-imagesubtitle-image-20008204125\" src=\"https://image.jimcdn.com/app/cms/image/transf/dimension=456x10000:format=png/path/s79e3f2024b935e45/image/if47a880e4e5bb635/version/1750857970/image.png\" alt=\"\" class=\"\" data-src-width=\"1280\" data-src-height=\"941\" data-src=\"https://image.jimcdn.com/app/cms/image/transf/dimension=456x10000:format=png/path/s79e3f2024b935e45/image/if47a880e4e5bb635/version/1750857970/image.png\" data-image-id=\"11909277925\"></a>    \n\n</figure>\n\n<div class=\"cc-clear\"></div>\n</div></div>    </div>\n            <div class=\"cc-m-hgrid-separator\" data-display=\"cms-only\"><div></div></div>\n        <div class=\"cc-m-hgrid-column last\" style=\"width: 49%;\">\n        <div id=\"cc-matrix-6111530225\"><div id=\"cc-m-20008204225\" class=\"j-module n j-header \"><h1 class=\"\" id=\"cc-m-header-20008204225\">Week-end culture malgache</h1></div><div id=\"cc-m-20008204325\" class=\"j-module n j-header \"><h2 class=\"\" id=\"cc-m-header-20008204325\">Dimanche 9 novembre</h2></div><div id=\"cc-m-20008204425\" class=\"j-module n j-header \"><h2 class=\"\" id=\"cc-m-header-20008204425\">Concert du dimanche</h2></div><div id=\"cc-m-20008204525\" class=\"j-module n j-text \"><p style=\"text-align: center;\">\n    <a href=\"https://www.mjctregunc.fr/%C3%A9v%C3%A9nements/programmation-sterenn/week-end-culturel-malgache/\" target=\"_blank\" title=\"https://www.mjctregunc.fr/%C3%A9v%C3%A9nements/programmation-sterenn/week-end-culturel-malgache/\"><span style=\"color: #454545;\"><strong>TRIO LAKA</strong></span></a>\n</p>\n\n<p>\n    &nbsp;\n</p>\n\n<p>\n    &nbsp;\n</p>\n\n<p>\n    &nbsp;\n</p></div><div id=\"cc-m-20008204625\" class=\"j-module n j-callToAction \"><div class=\"j-calltoaction-wrapper j-calltoaction-align-2\">\n    <a class=\"j-calltoaction-link j-calltoaction-link-style-3\" data-action=\"button\" href=\"https://www.mjctregunc.fr/événements/programmation-sterenn/week-end-culturel-malgache/\" target=\"_blank\" data-title=\"Voir le programme\">\n        Voir le programme    </a>\n</div>\n</div></div>    </div>\n    \n<div class=\"cc-m-hgrid-overlay\" data-display=\"cms-only\"></div>\n\n<br class=\"cc-clear\">","link":"https://www.mjctregunc.fr/%C3%A9v%C3%A9nements/programmation-sterenn/week-end-culturel-malgache/","retrieved":1764530898251},{"title":"Week-end culture malgache","contents":"<div class=\"cc-m-hgrid-column\" style=\"width: 49%;\">\n        <div id=\"cc-matrix-6111529625\"><div id=\"cc-m-20008202025\" class=\"j-module n j-imageSubtitle \"><figure class=\"cc-imagewrapper cc-m-image-align-1 cc-m-width-maxed\">\n<a href=\"https://www.mjctregunc.fr/événements/programmation-sterenn/week-end-culturel-malgache/\" target=\"_blank\"><img srcset=\"https://image.jimcdn.com/app/cms/image/transf/dimension=320x10000:format=jpg/path/s79e3f2024b935e45/image/i1fc951e248aafb27/version/1750857960/image.jpg 320w, https://image.jimcdn.com/app/cms/image/transf/dimension=456x10000:format=jpg/path/s79e3f2024b935e45/image/i1fc951e248aafb27/version/1750857960/image.jpg 456w, https://image.jimcdn.com/app/cms/image/transf/dimension=640x10000:format=jpg/path/s79e3f2024b935e45/image/i1fc951e248aafb27/version/1750857960/image.jpg 640w, https://image.jimcdn.com/app/cms/image/transf/dimension=912x10000:format=jpg/path/s79e3f2024b935e45/image/i1fc951e248aafb27/version/1750857960/image.jpg 912w\" sizes=\"(min-width: 456px) 456px, 100vw\" id=\"cc-m-imagesubtitle-image-20008202025\" src=\"https://image.jimcdn.com/app/cms/image/transf/dimension=456x10000:format=jpg/path/s79e3f2024b935e45/image/i1fc951e248aafb27/version/1750857960/image.jpg\" alt=\"\" class=\"\" data-src-width=\"1240\" data-src-height=\"930\" data-src=\"https://image.jimcdn.com/app/cms/image/transf/dimension=456x10000:format=jpg/path/s79e3f2024b935e45/image/i1fc951e248aafb27/version/1750857960/image.jpg\" data-image-id=\"11909277325\"></a>    \n\n</figure>\n\n<div class=\"cc-clear\"></div>\n</div></div>    </div>\n            <div class=\"cc-m-hgrid-separator\" data-display=\"cms-only\"><div></div></div>\n        <div class=\"cc-m-hgrid-column last\" style=\"width: 49%;\">\n        <div id=\"cc-matrix-6111529725\"><div id=\"cc-m-20008200825\" class=\"j-module n j-header \"><h1 class=\"\" id=\"cc-m-header-20008200825\">Week-end culture malgache</h1></div><div id=\"cc-m-20008200925\" class=\"j-module n j-header \"><h2 class=\"\" id=\"cc-m-header-20008200925\">Samedi 8 novembre</h2></div><div id=\"cc-m-20008203825\" class=\"j-module n j-header \"><h2 class=\"\" id=\"cc-m-header-20008203825\">Soirée culturelle</h2></div><div id=\"cc-m-20008201025\" class=\"j-module n j-text \"><p style=\"text-align: center;\">\n    <a href=\"https://www.mjctregunc.fr/%C3%A9v%C3%A9nements/programmation-sterenn/week-end-culturel-malgache/\" target=\"_blank\" title=\"https://www.mjctregunc.fr/%C3%A9v%C3%A9nements/programmation-sterenn/week-end-culturel-malgache/\"><span style=\"color: #454545;\"><strong>SOIRÉE FRANCO-MALGACHE</strong></span></a>\n</p>\n\n<p>\n    &nbsp;\n</p>\n\n<p>\n    &nbsp;\n</p>\n\n<p>\n    &nbsp;\n</p></div><div id=\"cc-m-20008201125\" class=\"j-module n j-callToAction \"><div class=\"j-calltoaction-wrapper j-calltoaction-align-2\">\n    <a class=\"j-calltoaction-link j-calltoaction-link-style-3\" data-action=\"button\" href=\"https://www.mjctregunc.fr/événements/programmation-sterenn/week-end-culturel-malgache/\" target=\"_blank\" data-title=\"Voir le programme\">\n        Voir le programme    </a>\n</div>\n</div></div>    </div>\n    \n<div class=\"cc-m-hgrid-overlay\" data-display=\"cms-only\"></div>\n\n<br class=\"cc-clear\">","link":"https://www.mjctregunc.fr/%C3%A9v%C3%A9nements/programmation-sterenn/week-end-culturel-malgache/","retrieved":1764530898251},{"title":"Concert ALRIGHT MELA","contents":"<div class=\"cc-m-hgrid-column\" style=\"width: 49%;\">\n        <div id=\"cc-matrix-6116397225\"><div id=\"cc-m-20035407225\" class=\"j-module n j-imageSubtitle \"><figure class=\"cc-imagewrapper cc-m-image-align-1 cc-m-width-maxed\">\n<a href=\"https://www.mjctregunc.fr/événements/programmation-sterenn/concert-de-saison/\" target=\"_blank\"><img srcset=\"https://image.jimcdn.com/app/cms/image/transf/dimension=320x10000:format=jpg/path/s79e3f2024b935e45/image/i5b453baef7c8cf65/version/1758095302/image.jpg 320w, https://image.jimcdn.com/app/cms/image/transf/dimension=456x10000:format=jpg/path/s79e3f2024b935e45/image/i5b453baef7c8cf65/version/1758095302/image.jpg 456w, https://image.jimcdn.com/app/cms/image/transf/dimension=640x10000:format=jpg/path/s79e3f2024b935e45/image/i5b453baef7c8cf65/version/1758095302/image.jpg 640w, https://image.jimcdn.com/app/cms/image/transf/dimension=912x10000:format=jpg/path/s79e3f2024b935e45/image/i5b453baef7c8cf65/version/1758095302/image.jpg 912w\" sizes=\"(min-width: 456px) 456px, 100vw\" id=\"cc-m-imagesubtitle-image-20035407225\" src=\"https://image.jimcdn.com/app/cms/image/transf/dimension=456x10000:format=jpg/path/s79e3f2024b935e45/image/i5b453baef7c8cf65/version/1758095302/image.jpg\" alt=\"\" class=\"\" data-src-width=\"2514\" data-src-height=\"2514\" data-src=\"https://image.jimcdn.com/app/cms/image/transf/dimension=456x10000:format=jpg/path/s79e3f2024b935e45/image/i5b453baef7c8cf65/version/1758095302/image.jpg\" data-image-id=\"11931840725\"></a>    \n\n</figure>\n\n<div class=\"cc-clear\"></div>\n</div></div>    </div>\n            <div class=\"cc-m-hgrid-separator\" data-display=\"cms-only\"><div></div></div>\n        <div class=\"cc-m-hgrid-column last\" style=\"width: 49%;\">\n        <div id=\"cc-matrix-6116397325\"><div id=\"cc-m-20035407325\" class=\"j-module n j-header \"><h1 class=\"\" id=\"cc-m-header-20035407325\">Concert&nbsp;ALRIGHT MELA</h1></div><div id=\"cc-m-20035407425\" class=\"j-module n j-header \"><h2 class=\"\" id=\"cc-m-header-20035407425\">Vendredi 10 octobre</h2></div><div id=\"cc-m-20035407525\" class=\"j-module n j-text \"><p style=\"text-align: left;\">\n    <a href=\"https://www.mjctregunc.fr/%C3%A9v%C3%A9nements/programmation-sterenn/concert-de-saison/\" target=\"_blank\" title=\"https://www.mjctregunc.fr/%C3%A9v%C3%A9nements/programmation-sterenn/concert-de-saison/\"><span style=\"color: #454545;\"><strong>MUSIQUE&nbsp;</strong></span></a><span style=\"color: #454545;\"><strong>TRANSE MÉDITERRÉNÉENNE</strong></span>\n</p></div><div id=\"cc-m-20035407625\" class=\"j-module n j-text \"><div id=\"cc-m-20034994825\" class=\"j-module n j-text\">\n    <p data-pm-slice=\"1 1 []\">\n        <span style=\"color: #454545;\">Alright Mela (original « orrajt mela ») : expression maltaise pouvant être traduite par « Tout va bien ! », synthétise bien leur musique arabo-européenne.</span>\n    </p>\n\n    <p>\n        <span style=\"color: #454545;\">Ancrés par des beats électroniques envoûtants et des synthés oldies hallucinés, le oud et le guembri sonnent la révolte pour que les chansons d’Alright Mela\n        donnent une irrésistible envie de danser le poing levé.</span>\n    </p>\n\n    <p>\n        <span style=\"color: #cc0000;\">&nbsp;</span>\n    </p>\n</div>\n\n<p>\n    &nbsp;\n</p></div><div id=\"cc-m-20035407725\" class=\"j-module n j-callToAction \"><div class=\"j-calltoaction-wrapper j-calltoaction-align-2\">\n    <a class=\"j-calltoaction-link j-calltoaction-link-style-3\" data-action=\"button\" href=\"https://www.mjctregunc.fr/événements/programmation-sterenn/concert-de-saison/\" target=\"_blank\" data-title=\"Voir le programme\">\n        Voir le programme    </a>\n</div>\n</div></div>    </div>\n    \n<div class=\"cc-m-hgrid-overlay\" data-display=\"cms-only\"></div>\n\n<br class=\"cc-clear\">","link":"https://www.mjctregunc.fr/%C3%A9v%C3%A9nements/programmation-sterenn/concert-de-saison/","retrieved":1764530898248},{"title":"Festival CAP Danse","contents":"<div class=\"cc-m-hgrid-column\" style=\"width: 49%;\">\n        <div id=\"cc-matrix-6111523725\"><div id=\"cc-m-20008173825\" class=\"j-module n j-imageSubtitle \"><figure class=\"cc-imagewrapper cc-m-image-align-1 cc-m-width-maxed\">\n<a href=\"https://www.mjctregunc.fr/événements/programmation-sterenn/festival-cap-danse/\" target=\"_blank\"><img srcset=\"https://image.jimcdn.com/app/cms/image/transf/dimension=320x10000:format=jpg/path/s79e3f2024b935e45/image/i4d1e74795799dc33/version/1750857012/image.jpg 320w, https://image.jimcdn.com/app/cms/image/transf/dimension=456x10000:format=jpg/path/s79e3f2024b935e45/image/i4d1e74795799dc33/version/1750857012/image.jpg 456w, https://image.jimcdn.com/app/cms/image/transf/dimension=640x10000:format=jpg/path/s79e3f2024b935e45/image/i4d1e74795799dc33/version/1750857012/image.jpg 640w, https://image.jimcdn.com/app/cms/image/transf/dimension=912x10000:format=jpg/path/s79e3f2024b935e45/image/i4d1e74795799dc33/version/1750857012/image.jpg 912w\" sizes=\"(min-width: 456px) 456px, 100vw\" id=\"cc-m-imagesubtitle-image-20008173825\" src=\"https://image.jimcdn.com/app/cms/image/transf/dimension=456x10000:format=jpg/path/s79e3f2024b935e45/image/i4d1e74795799dc33/version/1750857012/image.jpg\" alt=\"\" class=\"\" data-src-width=\"2000\" data-src-height=\"1258\" data-src=\"https://image.jimcdn.com/app/cms/image/transf/dimension=456x10000:format=jpg/path/s79e3f2024b935e45/image/i4d1e74795799dc33/version/1750857012/image.jpg\" data-image-id=\"11909268025\"></a>    \n\n</figure>\n\n<div class=\"cc-clear\"></div>\n</div></div>    </div>\n            <div class=\"cc-m-hgrid-separator\" data-display=\"cms-only\"><div></div></div>\n        <div class=\"cc-m-hgrid-column last\" style=\"width: 49%;\">\n        <div id=\"cc-matrix-6111523825\"><div id=\"cc-m-20008176325\" class=\"j-module n j-header \"><h1 class=\"\" id=\"cc-m-header-20008176325\">Festival CAP Danse</h1></div><div id=\"cc-m-20008197425\" class=\"j-module n j-header \"><h2 class=\"\" id=\"cc-m-header-20008197425\">Dimanche 28 septembre</h2></div><div id=\"cc-m-20008197925\" class=\"j-module n j-text \"><p style=\"text-align: left;\">\n    <a href=\"https://www.mjctregunc.fr/%C3%A9v%C3%A9nements/programmation-sterenn/festival-cap-danse/\" target=\"_blank\" title=\"https://www.mjctregunc.fr/%C3%A9v%C3%A9nements/programmation-sterenn/festival-cap-danse/\"><span style=\"color: #454545;\"><strong>BLIND DREAMS &gt; 10h30</strong></span></a>\n</p>\n\n<p style=\"text-align: left;\">\n    &nbsp;\n</p>\n\n<p style=\"text-align: left;\">\n    <a href=\"https://www.mjctregunc.fr/%C3%A9v%C3%A9nements/programmation-sterenn/festival-cap-danse/\" target=\"_blank\" title=\"https://www.mjctregunc.fr/%C3%A9v%C3%A9nements/programmation-sterenn/festival-cap-danse/\"><span style=\"color: #454545;\"><strong>AC/DC DUO POUR JULES ET STÉPHANE &gt;14h30</strong></span></a>\n</p>\n\n<p style=\"text-align: left;\">\n    &nbsp;\n</p>\n\n<p style=\"text-align: left;\">\n    <a href=\"https://www.mjctregunc.fr/%C3%A9v%C3%A9nements/programmation-sterenn/festival-cap-danse/\" target=\"_blank\" title=\"https://www.mjctregunc.fr/%C3%A9v%C3%A9nements/programmation-sterenn/festival-cap-danse/\"><span style=\"color: #454545;\"><strong>BAL DE CLÔTURE &gt;16h30</strong></span></a>\n</p>\n\n<p style=\"text-align: left;\">\n    &nbsp;\n</p></div><div id=\"cc-m-20008200025\" class=\"j-module n j-callToAction \"><div class=\"j-calltoaction-wrapper j-calltoaction-align-2\">\n    <a class=\"j-calltoaction-link j-calltoaction-link-style-3\" data-action=\"button\" href=\"https://www.mjctregunc.fr/événements/programmation-sterenn/festival-cap-danse/\" target=\"_blank\" data-title=\"Voir le programme\">\n        Voir le programme    </a>\n</div>\n</div></div>    </div>\n    \n<div class=\"cc-m-hgrid-overlay\" data-display=\"cms-only\"></div>\n\n<br class=\"cc-clear\">","link":"https://www.mjctregunc.fr/%C3%A9v%C3%A9nements/programmation-sterenn/festival-cap-danse/","retrieved":1764530898247},{"contents":"<div class=\"cc-m-hgrid-column\" style=\"width: 49%;\">\n        <div id=\"cc-matrix-6082175925\"><div id=\"cc-m-19851992625\" class=\"j-module n j-callToAction \"><div class=\"j-calltoaction-wrapper j-calltoaction-align-2\">\n    <a class=\"j-calltoaction-link j-calltoaction-link-style-3\" data-action=\"button\" href=\"https://www.mjctregunc.fr/événements/programmation/\" target=\"_blank\" data-title=\"Dates des spectacles\">\n        Dates des spectacles    </a>\n</div>\n</div></div>    </div>\n            <div class=\"cc-m-hgrid-separator\" data-display=\"cms-only\"><div></div></div>\n        <div class=\"cc-m-hgrid-column last\" style=\"width: 49%;\">\n        <div id=\"cc-matrix-6082176025\"><div id=\"cc-m-19851993725\" class=\"j-module n j-callToAction \"><div class=\"j-calltoaction-wrapper j-calltoaction-align-2\">\n    <a class=\"j-calltoaction-link j-calltoaction-link-style-3\" data-action=\"button\" href=\"https://mjctregunc.goasso.org/compte/inscription\" target=\"_blank\" data-title=\"Inscription CENTRE DE LOISIRS\">\n        Inscription CENTRE DE LOISIRS    </a>\n</div>\n</div></div>    </div>\n    \n<div class=\"cc-m-hgrid-overlay\" data-display=\"cms-only\"></div>\n\n<br class=\"cc-clear\">","retrieved":1765514142606},{"contents":"<div class=\"cc-m-hgrid-column\" style=\"width: 49%;\">\n        <div id=\"cc-matrix-6082174225\"><div id=\"cc-m-19851986325\" class=\"j-module n j-text \"><p>\n    HORAIRES D'ACCUEIL\n</p>\n\n<p>\n    <span style=\"font-size: 18px;\"><strong>Fermeture administrative du 22 décembre&nbsp; au 29 décembre inclus.</strong></span>\n</p>\n\n<ul>\n    <li>\n        <span style=\"font-size: 16px; line-height: 1.5;\">Mardi : 14h à 18h</span>\n    </li>\n\n    <li>\n        <span style=\"font-size: 16px; line-height: 1.5;\">Mercredi : 9h15 à 12h &amp; 14h à 18h</span>\n    </li>\n\n    <li>\n        <span style=\"font-size: 16px; line-height: 1.5;\">Jeudi : 9h15 à 12h &amp; 14h à 18h</span>\n    </li>\n\n    <li>\n        <span style=\"font-size: 16px;\">Vendredi : 9h15 à 12h &amp; 14h à 18h</span>\n    </li>\n\n    <li>\n        <span style=\"font-size: 16px;\">Samedi : 10h à 12h</span>\n    </li>\n</ul></div></div>    </div>\n            <div class=\"cc-m-hgrid-separator\" data-display=\"cms-only\"><div></div></div>\n        <div class=\"cc-m-hgrid-column last\" style=\"width: 49%;\">\n        <div id=\"cc-matrix-6082174325\"><div id=\"cc-m-20008667425\" class=\"j-module n j-text \"><p>\n    <span style=\"color: #b5a7d7; font-size: 16px;\"><strong><span style=\"line-height: 1.5;\">PÉRIODE VACANCES</span></strong></span>\n</p>\n\n<ul>\n    <li>\n        <span style=\"font-size: 16px;\"><span style=\"line-height: 1.5;\">Mardi :</span><span style=\"line-height: 1.5;\">&nbsp;</span>14h à 18h</span>\n    </li>\n\n    <li>\n        <span style=\"font-size: 16px; line-height: 1.5;\">Mercredi : 9h15 à 12h &amp; 14h à 18h</span>\n    </li>\n\n    <li>\n        <span style=\"font-size: 16px; line-height: 1.5;\">Jeudi : 9h15 à 12h &amp; 14h à 18h</span>\n    </li>\n\n    <li>\n        <span style=\"font-size: 16px; line-height: 1.5;\">Vendredi : 9h15 à 12h &amp; 14h à 18h</span>\n    </li>\n</ul></div></div>    </div>\n    \n<div class=\"cc-m-hgrid-overlay\" data-display=\"cms-only\"></div>\n\n<br class=\"cc-clear\">","retrieved":1765514142607},{"contents":"<div class=\"cc-m-hgrid-column\" style=\"width: 49%;\">\n        <div id=\"cc-matrix-6082174425\"><div id=\"cc-m-19851987725\" class=\"j-module n j-text \"><p style=\"text-align: left;\">\n    <span style=\"color: #b5a7d7;\"><strong>MJC LE STERENN</strong></span>\n</p>\n\n<p style=\"text-align: left;\">\n    <span style=\"font-size: 16px;\">Rue Jacques Prévert - 29910 Trégunc<strong><br></strong><span style=\"line-height: 1.7;\">Tél : 02 98 50 95 93</span></span>\n</p>\n\n<p>\n    <span style=\"font-size: 16px;\">Mail : <a href=\"mailto:contact@mjctregunc.fr\" title=\"contact@mjctregunc.fr\" class=\"\">contact@mjctregunc.fr</a></span>\n</p>\n\n<p>\n    &nbsp;\n</p></div><div id=\"cc-m-19916916425\" class=\"j-module n j-text \"><p>\n    <span style=\"font-weight: 700 !important; color: #b5a7d7; font-size: 16px;\">ACCUEIL DE LOISIRS&nbsp; (ALSH)</span>\n</p>\n\n<p>\n    <span style=\"font-size: 16px;\">Place Florestine Jeannès&nbsp;- 29910 Trégunc<span style=\"font-weight: 700 !important;\"><br></span><span style=\"line-height: 1.7;\">Tél&nbsp; :&nbsp;&nbsp; 02 98\n    50 41 53</span></span><span style=\"font-size: 16px;\"><a href=\"mailto:sahra@mjctregunc.fr\" class=\"\"><br></a><span style=\"white-space: nowrap;\">Mail : <a href=\"mailto:gabin@mjctregunc.fr\" title=\"mailto:gabin@mjctregunc.fr\" class=\"\">gabin@mjctregunc.fr</a></span></span>\n</p>\n\n<p>\n    &nbsp;\n</p></div></div>    </div>\n            <div class=\"cc-m-hgrid-separator\" data-display=\"cms-only\"><div></div></div>\n        <div class=\"cc-m-hgrid-column last\" style=\"width: 49%;\">\n        <div id=\"cc-matrix-6082174525\"><div id=\"cc-m-19851987525\" class=\"j-module n j-text \"><p>\n    <span style=\"font-weight: 700 !important; color: #ff9900; font-size: 16px;\"><span style=\"color: #b5a7d7;\">ESPACE JEUNES TRÉGUNC</span><br></span>\n</p>\n\n<p>\n    <span style=\"font-size: 16px;\">Rue Jacques Prévert - 29910 Trégunc<span style=\"font-weight: 700 !important;\"><br></span><span style=\"line-height: 1.7;\">Tél&nbsp; :&nbsp;&nbsp; 02 98 50 41 53\n    -&nbsp;</span></span><span style=\"font-size: 16px;\">Tél : 06 81 15 47 36</span><br>\n    <span style=\"font-size: 16px;\"><span style=\"line-height: 1.7;\">Mail :</span> <a href=\"mailto:sahra@mjctregunc.fr\" title=\"sahra@mjctregunc.fr\" class=\"\"><span style=\"white-space: nowrap;\">orane@mjctregunc.fr&nbsp;</span></a> <a href=\"mailto:sahra@mjctregunc.fr\" class=\"\"></a></span>\n</p>\n\n<p>\n    &nbsp;\n</p>\n\n<p>\n    <a href=\"mailto:sahra@mjctregunc.fr\" class=\"\"><span style=\"font-weight: 700 !important; color: #b5a7d7; font-size: 16px;\">ESPACE JEUNES PONT-AVEN</span><br></a><span style=\"font-size: 16px;\">Pontic Malo&nbsp; 29930 Pont-Aven</span>\n</p>\n\n<p>\n    <span style=\"font-size: 16px;\">Tél : 06 81 15 47 36<span style=\"font-weight: 700 !important;\"><br></span><span style=\"line-height: 1.7;\">Tél&nbsp; :&nbsp;&nbsp; 02 98 50 41\n    53</span></span><br>\n    <span style=\"font-size: 16px;\"><span style=\"line-height: 1.7;\">Mail :</span> orane<a href=\"mailto:sahra@mjctregunc.fr\" title=\"sahra@mjctregunc.fr\" class=\"\"><span style=\"white-space: nowrap;\">@mjctregunc.fr</span></a></span>\n</p>\n\n<p>\n    &nbsp;\n</p></div></div>    </div>\n    \n<div class=\"cc-m-hgrid-overlay\" data-display=\"cms-only\"></div>\n\n<br class=\"cc-clear\">","retrieved":1765514142609},{"contents":"<div class=\"cc-m-hgrid-column\" style=\"width: 20.79%;\">\n        <div id=\"cc-matrix-6088001825\"><div id=\"cc-m-19884293925\" class=\"j-module n j-imageSubtitle \"><figure class=\"cc-imagewrapper cc-m-image-align-3\">\n<a href=\"https://www.instagram.com/mjctregunc/\" target=\"_blank\"><img srcset=\"https://image.jimcdn.com/app/cms/image/transf/dimension=51x10000:format=png/path/s79e3f2024b935e45/image/i32c5ab0a492820c3/version/1723641166/image.png 51w, https://image.jimcdn.com/app/cms/image/transf/dimension=102x10000:format=png/path/s79e3f2024b935e45/image/i32c5ab0a492820c3/version/1723641166/image.png 102w\" sizes=\"(min-width: 51px) 51px, 100vw\" id=\"cc-m-imagesubtitle-image-19884293925\" src=\"https://image.jimcdn.com/app/cms/image/transf/dimension=51x10000:format=png/path/s79e3f2024b935e45/image/i32c5ab0a492820c3/version/1723641166/image.png\" alt=\"\" class=\"\" data-src-width=\"2000\" data-src-height=\"2000\" data-src=\"https://image.jimcdn.com/app/cms/image/transf/dimension=51x10000:format=png/path/s79e3f2024b935e45/image/i32c5ab0a492820c3/version/1723641166/image.png\" data-image-id=\"11803325225\"></a>    \n\n</figure>\n\n<div class=\"cc-clear\"></div>\n</div><div id=\"cc-m-19884295125\" class=\"j-module n j-text \"><p style=\"text-align: center;\">\n    Instagram MJC\n</p></div></div>    </div>\n            <div class=\"cc-m-hgrid-separator\" data-display=\"cms-only\"><div></div></div>\n        <div class=\"cc-m-hgrid-column\" style=\"width: 17.65%;\">\n        <div id=\"cc-matrix-5792132225\"><div id=\"cc-m-18696599125\" class=\"j-module n j-imageSubtitle \"><figure class=\"cc-imagewrapper cc-m-image-align-3\">\n<a href=\"mailto:contact@mjctregunc.fr\"><img srcset=\"https://image.jimcdn.com/app/cms/image/transf/dimension=48x10000:format=png/path/s79e3f2024b935e45/image/id6b6db3ec44c90ac/version/1596014502/image.png 48w, https://image.jimcdn.com/app/cms/image/transf/dimension=96x10000:format=png/path/s79e3f2024b935e45/image/id6b6db3ec44c90ac/version/1596014502/image.png 96w\" sizes=\"(min-width: 48px) 48px, 100vw\" id=\"cc-m-imagesubtitle-image-18696599125\" src=\"https://image.jimcdn.com/app/cms/image/transf/dimension=48x10000:format=png/path/s79e3f2024b935e45/image/id6b6db3ec44c90ac/version/1596014502/image.png\" alt=\"\" class=\"\" data-src-width=\"1024\" data-src-height=\"1024\" data-src=\"https://image.jimcdn.com/app/cms/image/transf/dimension=48x10000:format=png/path/s79e3f2024b935e45/image/id6b6db3ec44c90ac/version/1596014502/image.png\" data-image-id=\"10994672925\"></a>    \n\n</figure>\n\n<div class=\"cc-clear\"></div>\n</div></div>    </div>\n            <div class=\"cc-m-hgrid-separator\" data-display=\"cms-only\"><div></div></div>\n        <div class=\"cc-m-hgrid-column\" style=\"width: 14.11%;\">\n        <div id=\"cc-matrix-5792132325\"><div id=\"cc-m-18696599625\" class=\"j-module n j-imageSubtitle \"><figure class=\"cc-imagewrapper cc-m-image-align-3\">\n<a href=\"https://www.facebook.com/mjcdetregunc/\" target=\"_blank\"><img srcset=\"https://image.jimcdn.com/app/cms/image/transf/dimension=46x10000:format=png/path/s79e3f2024b935e45/image/i5d71170384ac76fa/version/1596014575/image.png 46w, https://image.jimcdn.com/app/cms/image/transf/dimension=92x10000:format=png/path/s79e3f2024b935e45/image/i5d71170384ac76fa/version/1596014575/image.png 92w\" sizes=\"(min-width: 46px) 46px, 100vw\" id=\"cc-m-imagesubtitle-image-18696599625\" src=\"https://image.jimcdn.com/app/cms/image/transf/dimension=46x10000:format=png/path/s79e3f2024b935e45/image/i5d71170384ac76fa/version/1596014575/image.png\" alt=\"\" class=\"\" data-src-width=\"1600\" data-src-height=\"1391\" data-src=\"https://image.jimcdn.com/app/cms/image/transf/dimension=46x10000:format=png/path/s79e3f2024b935e45/image/i5d71170384ac76fa/version/1596014575/image.png\" data-image-id=\"10994673325\"></a>    \n\n</figure>\n\n<div class=\"cc-clear\"></div>\n</div></div>    </div>\n            <div class=\"cc-m-hgrid-separator\" data-display=\"cms-only\"><div></div></div>\n        <div class=\"cc-m-hgrid-column\" style=\"width: 18.26%;\">\n        <div id=\"cc-matrix-5792132425\"><div id=\"cc-m-18696599425\" class=\"j-module n j-imageSubtitle \"><figure class=\"cc-imagewrapper cc-m-image-align-3\">\n<a href=\"https://www.instagram.com/espacejeunesmjctregunc/?hl=fr\" target=\"_blank\"><img srcset=\"https://image.jimcdn.com/app/cms/image/transf/dimension=40x10000:format=png/path/s79e3f2024b935e45/image/if1c6f7d9d9ed4e40/version/1596014617/image.png 40w, https://image.jimcdn.com/app/cms/image/transf/dimension=80x10000:format=png/path/s79e3f2024b935e45/image/if1c6f7d9d9ed4e40/version/1596014617/image.png 80w\" sizes=\"(min-width: 40px) 40px, 100vw\" id=\"cc-m-imagesubtitle-image-18696599425\" src=\"https://image.jimcdn.com/app/cms/image/transf/dimension=40x10000:format=png/path/s79e3f2024b935e45/image/if1c6f7d9d9ed4e40/version/1596014617/image.png\" alt=\"\" class=\"\" data-src-width=\"800\" data-src-height=\"800\" data-src=\"https://image.jimcdn.com/app/cms/image/transf/dimension=40x10000:format=png/path/s79e3f2024b935e45/image/if1c6f7d9d9ed4e40/version/1596014617/image.png\" data-image-id=\"10994673225\"></a>    \n\n</figure>\n\n<div class=\"cc-clear\"></div>\n</div><div id=\"cc-m-19884295425\" class=\"j-module n j-text \"><p style=\"text-align: center;\">\n    <span style=\"font-size: 13px;\">Espaces jeunes</span>\n</p></div></div>    </div>\n            <div class=\"cc-m-hgrid-separator\" data-display=\"cms-only\"><div></div></div>\n        <div class=\"cc-m-hgrid-column last\" style=\"width: 21.18%;\">\n        <div id=\"cc-matrix-5792135925\"><div id=\"cc-m-18696603425\" class=\"j-module n j-imageSubtitle \"><figure class=\"cc-imagewrapper cc-m-image-align-3\">\n<a href=\"https://soundcloud.com/mjc-tregunc\" target=\"_blank\"><img srcset=\"https://image.jimcdn.com/app/cms/image/transf/dimension=43x10000:format=jpg/path/s79e3f2024b935e45/image/ie74d8812807b1681/version/1690447997/image.jpg 43w, https://image.jimcdn.com/app/cms/image/transf/dimension=86x10000:format=jpg/path/s79e3f2024b935e45/image/ie74d8812807b1681/version/1690447997/image.jpg 86w\" sizes=\"(min-width: 43px) 43px, 100vw\" id=\"cc-m-imagesubtitle-image-18696603425\" src=\"https://image.jimcdn.com/app/cms/image/transf/dimension=43x10000:format=jpg/path/s79e3f2024b935e45/image/ie74d8812807b1681/version/1690447997/image.jpg\" alt=\"\" class=\"\" data-src-width=\"1667\" data-src-height=\"1667\" data-src=\"https://image.jimcdn.com/app/cms/image/transf/dimension=43x10000:format=jpg/path/s79e3f2024b935e45/image/ie74d8812807b1681/version/1690447997/image.jpg\" data-image-id=\"10994676425\"></a>    \n\n</figure>\n\n<div class=\"cc-clear\"></div>\n</div></div>    </div>\n    \n<div class=\"cc-m-hgrid-overlay\" data-display=\"cms-only\"></div>\n\n<br class=\"cc-clear\">","link":"https://www.instagram.com/mjctregunc/","retrieved":1764530898223},{"contents":"<div class=\"cc-m-hgrid-column\" style=\"width: 25.53%;\">\n        <div id=\"cc-matrix-6113274425\"><div id=\"cc-m-20017710725\" class=\"j-module n j-imageSubtitle \"><figure class=\"cc-imagewrapper cc-m-image-align-3\">\n<a href=\"https://www.finistere.fr/\" target=\"_blank\"><img srcset=\"https://image.jimcdn.com/app/cms/image/transf/dimension=214x10000:format=png/path/s79e3f2024b935e45/image/i0e640c4096c59cc9/version/1753362808/image.png 214w, https://image.jimcdn.com/app/cms/image/transf/dimension=320x10000:format=png/path/s79e3f2024b935e45/image/i0e640c4096c59cc9/version/1753362808/image.png 320w, https://image.jimcdn.com/app/cms/image/transf/dimension=428x10000:format=png/path/s79e3f2024b935e45/image/i0e640c4096c59cc9/version/1753362808/image.png 428w\" sizes=\"(min-width: 214px) 214px, 100vw\" id=\"cc-m-imagesubtitle-image-20017710725\" src=\"https://image.jimcdn.com/app/cms/image/transf/dimension=214x10000:format=png/path/s79e3f2024b935e45/image/i0e640c4096c59cc9/version/1753362808/image.png\" alt=\"\" class=\"\" data-src-width=\"2413\" data-src-height=\"1042\" data-src=\"https://image.jimcdn.com/app/cms/image/transf/dimension=214x10000:format=png/path/s79e3f2024b935e45/image/i0e640c4096c59cc9/version/1753362808/image.png\" data-image-id=\"11917620625\"></a>    \n\n</figure>\n\n<div class=\"cc-clear\"></div>\n</div></div>    </div>\n            <div class=\"cc-m-hgrid-separator\" data-display=\"cms-only\"><div></div></div>\n        <div class=\"cc-m-hgrid-column\" style=\"width: 25.02%;\">\n        <div id=\"cc-matrix-6113274725\"><div id=\"cc-m-20017717625\" class=\"j-module n j-spacing \">\n    <div class=\"cc-m-spacer\" style=\"height: 15px;\">\n    \n</div>\n\n</div><div id=\"cc-m-20017711125\" class=\"j-module n j-imageSubtitle \"><figure class=\"cc-imagewrapper cc-m-image-align-3 cc-m-width-maxed\">\n<a href=\"https://www.cca.bzh/\" target=\"_blank\"><img srcset=\"https://image.jimcdn.com/app/cms/image/transf/dimension=223x10000:format=png/path/s79e3f2024b935e45/image/i64b24d383c3feed2/version/1753362816/image.png 223w, https://image.jimcdn.com/app/cms/image/transf/dimension=320x10000:format=png/path/s79e3f2024b935e45/image/i64b24d383c3feed2/version/1753362816/image.png 320w, https://image.jimcdn.com/app/cms/image/transf/dimension=446x10000:format=png/path/s79e3f2024b935e45/image/i64b24d383c3feed2/version/1753362816/image.png 446w\" sizes=\"(min-width: 223px) 223px, 100vw\" id=\"cc-m-imagesubtitle-image-20017711125\" src=\"https://image.jimcdn.com/app/cms/image/transf/dimension=223x10000:format=png/path/s79e3f2024b935e45/image/i64b24d383c3feed2/version/1753362816/image.png\" alt=\"\" class=\"\" data-src-width=\"1577\" data-src-height=\"471\" data-src=\"https://image.jimcdn.com/app/cms/image/transf/dimension=223x10000:format=png/path/s79e3f2024b935e45/image/i64b24d383c3feed2/version/1753362816/image.png\" data-image-id=\"11917621025\"></a>    \n\n</figure>\n\n<div class=\"cc-clear\"></div>\n</div></div>    </div>\n            <div class=\"cc-m-hgrid-separator\" data-display=\"cms-only\"><div></div></div>\n        <div class=\"cc-m-hgrid-column\" style=\"width: 16.62%;\">\n        <div id=\"cc-matrix-6113274625\"><div id=\"cc-m-20017711625\" class=\"j-module n j-imageSubtitle \"><figure class=\"cc-imagewrapper cc-m-image-align-3\">\n<a href=\"https://www.tregunc.fr/\" target=\"_blank\"><img srcset=\"https://image.jimcdn.com/app/cms/image/transf/dimension=109x10000:format=png/path/s79e3f2024b935e45/image/i14c63ca64a11cb6b/version/1753363125/image.png 109w, https://image.jimcdn.com/app/cms/image/transf/dimension=218x10000:format=png/path/s79e3f2024b935e45/image/i14c63ca64a11cb6b/version/1753363125/image.png 218w\" sizes=\"(min-width: 109px) 109px, 100vw\" id=\"cc-m-imagesubtitle-image-20017711625\" src=\"https://image.jimcdn.com/app/cms/image/transf/dimension=109x10000:format=png/path/s79e3f2024b935e45/image/i14c63ca64a11cb6b/version/1753363125/image.png\" alt=\"\" class=\"\" data-src-width=\"509\" data-src-height=\"509\" data-src=\"https://image.jimcdn.com/app/cms/image/transf/dimension=109x10000:format=png/path/s79e3f2024b935e45/image/i14c63ca64a11cb6b/version/1753363125/image.png\" data-image-id=\"11917621425\"></a>    \n\n</figure>\n\n<div class=\"cc-clear\"></div>\n</div></div>    </div>\n            <div class=\"cc-m-hgrid-separator\" data-display=\"cms-only\"><div></div></div>\n        <div class=\"cc-m-hgrid-column last\" style=\"width: 26.82%;\">\n        <div id=\"cc-matrix-6113274525\"><div id=\"cc-m-20017717425\" class=\"j-module n j-spacing \">\n    <div class=\"cc-m-spacer\" style=\"height: 15px;\">\n    \n</div>\n\n</div><div id=\"cc-m-20008669525\" class=\"j-module n j-imageSubtitle \"><figure class=\"cc-imagewrapper cc-m-image-align-1 cc-m-width-maxed\">\n<a href=\"https://pontaven.fr/\" target=\"_blank\"><img srcset=\"https://image.jimcdn.com/app/cms/image/transf/dimension=213x10000:format=png/path/s79e3f2024b935e45/image/ie7fe3eb002dc3e5b/version/1753363171/image.png 213w, https://image.jimcdn.com/app/cms/image/transf/dimension=320x10000:format=png/path/s79e3f2024b935e45/image/ie7fe3eb002dc3e5b/version/1753363171/image.png 320w, https://image.jimcdn.com/app/cms/image/transf/dimension=426x10000:format=png/path/s79e3f2024b935e45/image/ie7fe3eb002dc3e5b/version/1753363171/image.png 426w\" sizes=\"(min-width: 213px) 213px, 100vw\" id=\"cc-m-imagesubtitle-image-20008669525\" src=\"https://image.jimcdn.com/app/cms/image/transf/dimension=213x10000:format=png/path/s79e3f2024b935e45/image/ie7fe3eb002dc3e5b/version/1753363171/image.png\" alt=\"\" class=\"\" data-src-width=\"1633\" data-src-height=\"433\" data-src=\"https://image.jimcdn.com/app/cms/image/transf/dimension=213x10000:format=png/path/s79e3f2024b935e45/image/ie7fe3eb002dc3e5b/version/1753363171/image.png\" data-image-id=\"11909610625\"></a>    \n\n</figure>\n\n<div class=\"cc-clear\"></div>\n</div></div>    </div>\n    \n<div class=\"cc-m-hgrid-overlay\" data-display=\"cms-only\"></div>\n\n<br class=\"cc-clear\">","link":"https://www.finistere.fr/","retrieved":1764530898228}]}